{"nodes": [{"id": "d_krupali_event_management_client_src_components_tickets_ticketcard_tsx", "label": "TicketCard.tsx", "file_type": "code", "source_file": "D:\\krupali\\Event_Management\\client\\src\\components\\tickets\\TicketCard.tsx", "source_location": "L1"}, {"id": "ticketcard_formatcurrency", "label": "formatCurrency()", "file_type": "code", "source_file": "D:\\krupali\\Event_Management\\client\\src\\components\\tickets\\TicketCard.tsx", "source_location": "L15"}, {"id": "ticketcard_formatdatetime", "label": "formatDateTime()", "file_type": "code", "source_file": "D:\\krupali\\Event_Management\\client\\src\\components\\tickets\\TicketCard.tsx", "source_location": "L27"}], "edges": [{"source": "d_krupali_event_management_client_src_components_tickets_ticketcard_tsx", "target": "lucide_react", "relation": "imports_from", "confidence": "EXTRACTED", "source_file": "D:\\krupali\\Event_Management\\client\\src\\components\\tickets\\TicketCard.tsx", "source_location": "L1", "weight": 1.0}, {"source": "d_krupali_event_management_client_src_components_tickets_ticketcard_tsx", "target": "button", "relation": "imports_from", "confidence": "EXTRACTED", "source_file": "D:\\krupali\\Event_Management\\client\\src\\components\\tickets\\TicketCard.tsx", "source_location": "L2", "weight": 1.0}, {"source": "d_krupali_event_management_client_src_components_tickets_ticketcard_tsx", "target": "card", "relation": "imports_from", "confidence": "EXTRACTED", "source_file": "D:\\krupali\\Event_Management\\client\\src\\components\\tickets\\TicketCard.tsx", "source_location": "L3", "weight": 1.0}, {"source": "d_krupali_event_management_client_src_components_tickets_ticketcard_tsx", "target": "ticket_types", "relation": "imports_from", "confidence": "EXTRACTED", "source_file": "D:\\krupali\\Event_Management\\client\\src\\components\\tickets\\TicketCard.tsx", "source_location": "L4", "weight": 1.0}, {"source": "d_krupali_event_management_client_src_components_tickets_ticketcard_tsx", "target": "d_krupali_event_management_client_src_components_tickets_ticketstatusbadge", "relation": "imports_from", "confidence": "EXTRACTED", "source_file": "D:\\krupali\\Event_Management\\client\\src\\components\\tickets\\TicketCard.tsx", "source_location": "L5", "weight": 1.0}, {"source": "d_krupali_event_management_client_src_components_tickets_ticketcard_tsx", "target": "ticketcard_formatcurrency", "relation": "contains", "confidence": "EXTRACTED", "source_file": "D:\\krupali\\Event_Management\\client\\src\\components\\tickets\\TicketCard.tsx", "source_location": "L15", "weight": 1.0}, {"source": "d_krupali_event_management_client_src_components_tickets_ticketcard_tsx", "target": "ticketcard_formatdatetime", "relation": "contains", "confidence": "EXTRACTED", "source_file": "D:\\krupali\\Event_Management\\client\\src\\components\\tickets\\TicketCard.tsx", "source_location": "L27", "weight": 1.0}], "raw_calls": [{"caller_nid": "ticketcard_formatcurrency", "callee": "format", "source_file": "D:\\krupali\\Event_Management\\client\\src\\components\\tickets\\TicketCard.tsx", "source_location": "L20"}, {"caller_nid": "ticketcard_formatdatetime", "callee": "toLocaleDateString", "source_file": "D:\\krupali\\Event_Management\\client\\src\\components\\tickets\\TicketCard.tsx", "source_location": "L28"}]}